{
	"$schema": "../../../meta/definitions/card.schema.json",
	"abilities": [
		{
			"type": "Poke-BODY",
			"name": {
				"en": "WALL",
				"fr": "WALL"
			},
			"effect": {
				"en": "As long as Unown W is your Active Pokémon, any damage done to your Pokémon by an opponent's attack is reduced by 10 (after applying Weakness and Resistance).",
				"fr": "Tant que Zarbi V est votre Pokémon Actif, tous dégâts infligés à vos Pokémon par une attaque de votre adversaire sont réduits de 10 (après application de la Faiblesse et de la Résistance)."
			}
		}
	],
	"attacks": [
		{
			"cost": [
				"Psychic",
				"Colorless",
				"Colorless"
			],
			"name": {
				"en": "Hidden Power",
				"fr": "Puissance cachée"
			},
			"effect": {
				"en": "Draw a card.",
				"fr": "Piochez une carte."
			},
			"damage": 50
		}
	],
	"category": "Pokemon",
	"description": {
		"fr": "Il rappelle une écriture ancienne. Reste à savoir qui du langage ou de ZARBI est apparu en premier."
	},
	"dexId": [
		201
	],
	"hp": 90,
	"illustrator": [
		"Kazuaki Aihara"
	],
	"name": {
		"en": "Unown W",
		"fr": "Zarbi W"
	},
	"rarity": "Uncommon",
	"retreat": 3,
	"set": "dp6",
	"stage": "Basic",
	"types": [
		"Psychic"
	],
	"weaknesses": [
		{
			"type": "Psychic",
			"value": "+30"
		}
	]
}