{
	"$schema": "../../../meta/definitions/card.schema.json",
	"abilities": [
		{
			"type": "Poke-BODY",
			"name": {
				"en": "Pure Body"
			},
			"effect": {
				"en": "To attach a Water Energy card from your hand to Suicune, you must discard an Energy card attached to Suicune. (Attach the Water Energy, and then discard an Energy card from Suicune.)"
			}
		}
	],
	"attacks": [
		{
			"cost": [
				"Water",
				"Colorless",
				"Colorless"
			],
			"name": {
				"en": "Hypno Wave"
			},
			"effect": {
				"en": "Flip a coin. If heads, this attack does 30 damage plus 20 more damage. If tails, this attack does 30 damage and the Defending Pokémon is now Asleep."
			},
			"damage": 30
		}
	],
	"category": "Pokemon",
	"dexId": [
		245
	],
	"hp": 70,
	"illustrator": "Atsuko Nishida",
	"name": {
		"en": "Suicune"
	},
	"rarity": "Common",
	"set": "basep",
	"stage": "Basic",
	"types": [
		"Water"
	],
	"weaknesses": [
		{
			"type": "Lightning",
			"value": "×2"
		}
	]
}