{
	"$schema": "../../../meta/definitions/card.schema.json",
	"category": "Trainer",
	"effect": {
		"en": "Flip 2 coins. If both are heads, put a card from your discard pile into your hand.",
		"fr": "Lancez 2 pièces. Si les deux sont face, ajoutez une carte de votre pile de défausse à votre main.",
		"es": "Lanza 2 monedas. Si ambas son cara, pon 1 carta de tu pila de descartes en tu mano.",
		"it": "Lancia due volte una moneta. Se esce entrambe le volte testa, prendi una carta dalla tua pila degli scarti e aggiungila a quelle che hai in mano.",
		"pt": "Jogue 2 moedas. Se ambas saírem cara, coloque 1 carta da sua pilha de descarte na sua mão.",
		"de": "Wirf 2 Münzen. Zeigen beide Kopf, nimm 1 Karte aus deinem Ablagestapel auf deine Hand."
	},
	"illustrator": [
		"Studio Bora Inc."
	],
	"name": {
		"de": "Alter PC",
		"en": "Old PC",
		"es": "Ordenador Antiguo",
		"fr": "Vieux PC",
		"it": "Vecchio PC",
		"pt": "Computador Antigo"
	},
	"rarity": "Uncommon",
	"regulationMark": "D",
	"set": "swsh3",
	"trainerType": "Item",
	"variants": {
		"normal": true,
		"reverse": true,
		"holo": false,
		"firstEdition": false
	}
}