{
	"$schema": "../../../meta/definitions/card.schema.json",
	"attacks": [
		{
			"cost": [
				"Grass"
			],
			"name": {
				"en": "Bemusing Aroma",
				"fr": "Parfum Troublant"
			},
			"effect": {
				"en": "Flip a coin. If heads, the Defending Pokémon is now Paralyzed and Poisoned. If tails, the Defending Pokémon is now Confused.",
				"fr": "Lancez une pièce. Si c'est face, le Pokémon Défenseur est maintenant Paralysé et Empoisonné. Si c'est pile, le Pokémon Défenseur est maintenant Confus."
			},
			"damage": 20
		},
		{
			"cost": [
				"Grass",
				"Colorless",
				"Colorless"
			],
			"name": {
				"en": "Cut",
				"fr": "Coupe"
			},
			"damage": 60
		}
	],
	"category": "Pokemon",
	"dexId": [
		549
	],
	"evolveFrom": {
		"en": "Petilil",
		"fr": "Chlorobule"
	},
	"hp": 90,
	"illustrator": [
		"Shin Nagasawa"
	],
	"name": {
		"de": "Dressella",
		"en": "Lilligant",
		"es": "Lilligant",
		"fr": "Fragilady",
		"it": "Lilligant",
		"pt": "Lilligant"
	},
	"rarity": "Uncommon",
	"resistances": [
		{
			"type": "Water",
			"value": "-20"
		}
	],
	"retreat": 1,
	"set": "bw2",
	"stage": "Stage1",
	"types": [
		"Grass"
	],
	"weaknesses": [
		{
			"type": "Fire",
			"value": "×2"
		}
	]
}