{
	"$schema": "../../../meta/definitions/card.schema.json",
	"attacks": [
		{
			"cost": [
				"Colorless"
			],
			"name": {
				"en": "Hop",
				"fr": "Hop"
			},
			"damage": 20
		},
		{
			"cost": [
				"Grass"
			],
			"name": {
				"en": "Mysterious Powder",
				"fr": "Poudre mystérieuse"
			},
			"effect": {
				"en": "Flip a coin. If heads, the Defending Pokémon is now Confused.",
				"fr": "Lancez une pièce. Si c'est face, le Pokémon Défenseur est maintenant Confus."
			},
			"damage": 10
		}
	],
	"category": "Pokemon",
	"description": {
		"fr": "Il écarte ses pétales pour absorber la lumière du soleil. Il flotte aussi dans les airs pour se rapprocher de l'astre du jour."
	},
	"dexId": [
		188
	],
	"evolveFrom": {
		"en": "Hoppip"
	},
	"hp": 60,
	"illustrator": [
		"Mitsuhiro Arita"
	],
	"name": {
		"en": "Skiploom",
		"fr": "Floravol"
	},
	"rarity": "Common",
	"resistances": [
		{
			"type": "Fighting",
			"value": "-30"
		}
	],
	"set": "neo3",
	"stage": "Stage1",
	"types": [
		"Grass"
	],
	"weaknesses": [
		{
			"type": "Fire",
			"value": "×2"
		}
	]
}