{
	"$schema": "../../../meta/definitions/card.schema.json",
	"attacks": [
		{
			"cost": [
				"Colorless"
			],
			"name": {
				"en": "Razor Leaf",
				"fr": "Tranch'Herbe"
			},
			"damage": 10
		}
	],
	"category": "Pokemon",
	"dexId": [
		669
	],
	"hp": 40,
	"illustrator": [
		"Saya Tsuruta"
	],
	"name": {
		"en": "Flabébé",
		"fr": "Flabébé"
	},
	"rarity": "Common",
	"resistances": [
		{
			"type": "Darkness",
			"value": "-20"
		}
	],
	"retreat": 1,
	"set": "g1",
	"stage": "Basic",
	"types": [
		"Fairy"
	],
	"weaknesses": [
		{
			"type": "Metal",
			"value": "×2"
		}
	]
}