{
	"$schema": "../../../meta/definitions/card.schema.json",
	"abilities": [
		{
			"type": "Pokemon Power",
			"name": {
				"en": "Kabuto Armor",
				"fr": "Armure Kabuto"
			},
			"effect": {
				"en": "Whenever an attack (even your own) does damage to Kabuto (after applying Weakness and Resistance), that attack only does half the damage to Kabuto (rounded down to nearest 10). (Any other effects of attacks still happen.) This power stops working while Kabuto is Asleep, Confused, or Paralyzed.",
				"fr": "Chaque fois qu'une attaque (même la vôtre) inflige des dégâts à Kabuto (après application de la Faiblesse et de la Résistance), cette attaque inflige seulement la moitié des dégâts à Kabuto (arrondis à la dizaine la plus proche). (Tout autre effet ou attaque intervient toujours.) L'effet de ce pouvoir cesse lorsque Kabuto est Endormi, Confus ou Paralysé."
			}
		}
	],
	"attacks": [
		{
			"cost": [
				"Colorless"
			],
			"name": {
				"en": "Scratch",
				"fr": "Griffe"
			},
			"damage": 10
		}
	],
	"category": "Pokemon",
	"description": {
		"fr": "Disparu depuis longtemps, il peut être réanimé génétiquement à partir d'anciens fossiles."
	},
	"dexId": [
		140
	],
	"hp": 30,
	"illustrator": [
		"Ken Sugimori"
	],
	"name": {
		"en": "Kabuto",
		"fr": "Kabuto"
	},
	"rarity": "Common",
	"set": "base3",
	"stage": "Stage1",
	"types": [
		"Fighting"
	],
	"variants": {
		"wPromo": true
	},
	"weaknesses": [
		{
			"type": "Grass",
			"value": "×2"
		}
	]
}