{
	"$schema": "../../../meta/definitions/card.schema.json",
	"attacks": [
		{
			"cost": [
				"Fighting",
				"Colorless"
			],
			"name": {
				"en": "Retaliate"
			},
			"effect": {
				"en": "If any of your Pokémon were Knocked Out by damage from an opponent's attack during his or her last turn, this attack does 60 more damage."
			},
			"damage": 30
		},
		{
			"cost": [
				"Fighting",
				"Fighting",
				"Colorless"
			],
			"name": {
				"en": "Land Crush"
			},
			"damage": 90
		}
	],
	"category": "Pokemon",
	"dexId": [
		639
	],
	"hp": 130,
	"illustrator": "Shigenori Negishi",
	"name": {
		"en": "Terrakion"
	},
	"rarity": "Rare",
	"retreat": 4,
	"set": "bw11",
	"stage": "Basic",
	"types": [
		"Fighting"
	],
	"weaknesses": [
		{
			"type": "Grass",
			"value": "×2"
		}
	]
}