{
	"$schema": "../../../meta/definitions/card.schema.json",
	"abilities": [
		{
			"type": "Poke-POWER",
			"name": {
				"en": "Second Sight",
				"fr": "Seconde vue"
			},
			"effect": {
				"en": "Once during your turn (before your attack), you may look at the top 3 cards of either player’s deck and put them back on top of that player’s deck in any order. This power can’t be used if Slowking is affected by a Special Condition.",
				"fr": "Une seule fois pendant votre tour (avant votre attaque), vous pouvez regarder les 3 cartes du dessus du deck de n’importe quel joueur et les y replacer dans l’ordre de votre choix. Ce pouvoir ne peut pas être utilisé si Roigada est affecté par un État spécial."
			}
		}
	],
	"attacks": [
		{
			"cost": [
				"Psychic",
				"Colorless"
			],
			"name": {
				"en": "Psyshock",
				"fr": "Choc psy"
			},
			"effect": {
				"en": "Flip a coin. If heads, the Defending Pokémon is now Paralyzed.",
				"fr": "Lancez une pièce. Si c’est face, le Pokémon Défenseur est maintenant Paralysé."
			},
			"damage": 30
		}
	],
	"category": "Pokemon",
	"description": {
		"en": "It has incredible intellect and intuition. Whatever the situation, it remains calm and collected."
	},
	"dexId": [
		199
	],
	"evolveFrom": {
		"en": "Slowpoke",
		"fr": "Ramoloss"
	},
	"hp": 80,
	"illustrator": [
		"Sumiyoshi Kizuki"
	],
	"name": {
		"en": "Slowking",
		"fr": "Roigada"
	},
	"rarity": "Rare",
	"retreat": 2,
	"set": "hgss1",
	"stage": "Stage1",
	"types": [
		"Psychic"
	],
	"variants": {
		"normal": false,
		"reverse": false,
		"holo": true,
		"firstEdition": false
	},
	"weaknesses": [
		{
			"type": "Psychic",
			"value": "×2"
		}
	]
}