{
	"$schema": "../../../meta/definitions/card.schema.json",
	"attacks": [
		{
			"cost": [
				"Colorless",
				"Colorless"
			],
			"name": {
				"en": "Double Kick",
				"fr": "Double Pied",
				"es": "Doble Patada",
				"it": "Doppiocalico",
				"pt": "Chute Duplo",
				"de": "Doppelkick"
			},
			"effect": {
				"en": "Flip 2 coins. This attack does 30 damage for each heads.",
				"fr": "Lancez 2 pièces. Cette attaque inflige 30 dégâts multipliés par le nombre de côtés face.",
				"es": "Lanza 2 monedas. Este ataque hace 30 puntos de daño por cada cara.",
				"it": "Lancia due volte una moneta. Questo attacco infligge 30 danni ogni volta che esce testa.",
				"pt": "Jogue 2 moedas. Este ataque causa 30 pontos de dano para cada cara.",
				"de": "Wirf 2 Münzen. Diese Attacke fügt 30 Schadenspunkte pro Kopf zu."
			},
			"damage": "30×"
		},
		{
			"cost": [
				"Fire",
				"Fire",
				"Colorless"
			],
			"name": {
				"en": "Flamethrower",
				"fr": "Lance-Flammes",
				"es": "Lanzallamas",
				"it": "Lanciafiamme",
				"pt": "Lança-chamas",
				"de": "Flammenwurf"
			},
			"effect": {
				"en": "Discard an Energy from this Pokémon.",
				"fr": "Défaussez une Énergie de ce Pokémon.",
				"es": "Descarta 1 Energía de este Pokémon.",
				"it": "Scarta un’Energia assegnata a questo Pokémon.",
				"pt": "Descarte 1 Energia deste Pokémon.",
				"de": "Lege 1 Energie von diesem Pokémon auf deinen Ablagestapel."
			},
			"damage": 80
		}
	],
	"category": "Pokemon",
	"dexId": [
		256
	],
	"evolveFrom": {
		"en": "Torchic",
		"fr": "Poussifeu"
	},
	"hp": 80,
	"illustrator": [
		"Mizue"
	],
	"name": {
		"de": "Jungglut",
		"en": "Combusken",
		"es": "Combusken",
		"fr": "Galifeu",
		"it": "Combusken",
		"pt": "Combusken"
	},
	"rarity": "Uncommon",
	"retreat": 1,
	"set": "sm7",
	"stage": "Stage1",
	"types": [
		"Fire"
	],
	"weaknesses": [
		{
			"type": "Water",
			"value": "×2"
		}
	]
}