{
	"$schema": "../../../meta/definitions/card.schema.json",
	"abilities": [
		{
			"type": "Poke-BODY",
			"name": {
				"en": "Thick Fat",
				"fr": "Isograisse"
			},
			"effect": {
				"en": "Any damage done to Azumarill by attacks from Fire Pokémon and Water Pokémon is reduced by 30 (after applying Weakness and Resistance).",
				"fr": "Tous dégâts infligés à Azumarill par des attaques de Pokémon  et  sont réduits de 30 (après application de la Faiblesse et de la Résistance)."
			}
		}
	],
	"attacks": [
		{
			"cost": [
				"Water",
				"Water",
				"Colorless"
			],
			"name": {
				"en": "Bubblebeam",
				"fr": "Bulles d'O"
			},
			"effect": {
				"en": "Flip a coin. If heads, the Defending Pokémon is now Paralyzed.",
				"fr": "Lancez une pièce. Si c'est face, le Pokémon Défenseur est maintenant Paralysé."
			},
			"damage": 40
		}
	],
	"category": "Pokemon",
	"dexId": [
		184
	],
	"evolveFrom": {
		"en": "Marill"
	},
	"hp": 70,
	"illustrator": [
		"Kagemaru Himeno"
	],
	"name": {
		"en": "Azumarill",
		"fr": "Azumarill"
	},
	"rarity": "Rare",
	"set": "ex11",
	"stage": "Stage1",
	"types": [
		"Water"
	],
	"weaknesses": [
		{
			"type": "Lightning",
			"value": "×2"
		}
	]
}