{
	"$schema": "../../../meta/definitions/card.schema.json",
	"attacks": [
		{
			"cost": [
				"Fighting"
			],
			"name": {
				"en": "Sand Jet",
				"fr": "Sablage"
			},
			"effect": {
				"en": "This attack does 20 damage to 1 of your opponent's Benched Pokémon. (Don't apply Weakness and Resistance for Benched Pokémon.)",
				"fr": "Cette attaque inflige 20 dégâts à 1 des Pokémon de Banc de votre adversaire. (N'appliquez ni la Faiblesse ni la Résistance aux Pokémon de Banc.)"
			}
		},
		{
			"cost": [
				"Fighting",
				"Colorless",
				"Colorless"
			],
			"name": {
				"en": "Bite",
				"fr": "Morsure"
			},
			"damage": 30
		}
	],
	"category": "Pokemon",
	"dexId": [
		449
	],
	"hp": 90,
	"illustrator": [
		"match"
	],
	"name": {
		"de": "Hippopotas",
		"en": "Hippopotas",
		"es": "Hippopotas",
		"fr": "Hippopotas",
		"it": "Hippopotas",
		"pt": "Hippopotas"
	},
	"rarity": "Common",
	"resistances": [
		{
			"type": "Lightning",
			"value": "-20"
		}
	],
	"retreat": 4,
	"set": "bw4",
	"stage": "Basic",
	"types": [
		"Fighting"
	],
	"weaknesses": [
		{
			"type": "Water",
			"value": "×2"
		}
	]
}