{
	"$schema": "../../../meta/definitions/card.schema.json",
	"abilities": [
		{
			"type": "Ability",
			"name": {
				"en": "Slip Trip",
				"fr": "Bave Glissante",
				"es": "Paseo Escurridizo",
				"it": "Scivolavia",
				"pt": "Escorregada",
				"de": "Rutschiger Weg"
			},
			"effect": {
				"en": "Each player can't attach any Pokémon Tool cards from his or her hand to any of his or her Pokémon.",
				"fr": "Aucun joueur ne peut attacher de carte Outil Pokémon de sa main à ses Pokémon.",
				"es": "Los jugadores no pueden unir ninguna carta de Herramienta Pokémon de su mano a ninguno de sus Pokémon.",
				"it": "Nessun giocatore può assegnare delle carte Oggetto Pokémon dalla propria mano ai suoi Pokémon.",
				"pt": "Nenhum jogador pode ligar cards de Ferramenta Pokémon da própria mão a nenhum dos Pokémon do jogador.",
				"de": "Kein Spieler darf Pokémon-Ausrüstungen von seiner Hand an seine Pokémon anlegen."
			}
		}
	],
	"attacks": [
		{
			"cost": [
				"Water",
				"Fairy",
				"Colorless",
				"Colorless"
			],
			"name": {
				"en": "Dragon Pulse",
				"fr": "Dracochoc",
				"es": "Pulso Dragón",
				"it": "Dragopulsar",
				"pt": "Pulso do Dragão",
				"de": "Drachenpuls"
			},
			"effect": {
				"en": "Discard the top card of your deck.",
				"fr": "Défaussez la carte du dessus de votre deck.",
				"es": "Descarta la primera carta de tu baraja.",
				"it": "Scarta la prima carta del tuo mazzo.",
				"pt": "Descarte o card de cima do seu baralho.",
				"de": "Lege die oberste Karte deines Decks auf deinen Ablagestapel."
			},
			"damage": 130
		}
	],
	"category": "Pokemon",
	"dexId": [
		706
	],
	"evolveFrom": {
		"en": "Sliggoo",
		"fr": "Colimucus",
		"es": "Sliggoo",
		"it": "Sliggoo",
		"pt": "Sliggoo",
		"de": "Viscargot"
	},
	"hp": 140,
	"illustrator": "5ban Graphics",
	"name": {
		"de": "Viscogon",
		"en": "Goodra",
		"es": "Goodra",
		"fr": "Muplodocus",
		"it": "Goodra",
		"pt": "Goodra"
	},
	"rarity": "Rare",
	"retreat": 3,
	"set": "xy4",
	"stage": "Stage2",
	"types": [
		"Dragon"
	],
	"weaknesses": [
		{
			"type": "Fairy",
			"value": "×2"
		}
	]
}